fp_cate/__init__.py
fp_cate/cates/__init__.py
fp_cate/cates/_internal.py
fp_cate/cates/cates.py
fp_cate/control/__init__.py
fp_cate/control/flow.py
fp_cate/control/pattern_match.py
fp_cate/extra/__init__.py
fp_cate/extra/_internal/placeholder.py
fp_cate/extra/macro.py
fp_cate/extra/qlambda.py
fp_cate/ops/__init__.py
fp_cate/ops/dict.py
fp_cate/ops/list.py
fp_cate/optimize/__init__.py
fp_cate/optimize/tco.py
fp_cate/py.typed
fp_cate/qlambda/__init__.py
fp_cate/qlambda/_internal.py
fp_cate/utils.py
fp_cate-0.1.17.dist-info/WHEEL
fp_cate-0.1.17.dist-info/METADATA
fp_cate-0.1.17.dist-info/RECORD
