Metadata-Version: 2.3
Name: fp-cate
Version: 0.1.17
Summary: Functional programming tools for Python
Author: BrandenXia
Author-email: BrandenXia <xxtbranden@outlook.com>
Requires-Dist: typing-extensions>=4.15.0
Requires-Python: >=3.10
